visualize/__init__.py
visualize/edit_graphviz_svg.py
visualize/embed_svg.py
visualize/jsonify.py
unfolding_vis-1.0.1.dist-info/LICENSE
unfolding_vis-1.0.1.dist-info/METADATA
unfolding_vis-1.0.1.dist-info/WHEEL
unfolding_vis-1.0.1.dist-info/top_level.txt
unfolding_vis-1.0.1.dist-info/RECORD
